soroban/.DS_Store
soroban/__init__.py
soroban-1.0.0.dist-info/METADATA
soroban-1.0.0.dist-info/WHEEL
soroban-1.0.0.dist-info/RECORD
